torch_eunn.py
torch_eunn-0.2.1.dist-info/LICENSE
torch_eunn-0.2.1.dist-info/METADATA
torch_eunn-0.2.1.dist-info/WHEEL
torch_eunn-0.2.1.dist-info/top_level.txt
torch_eunn-0.2.1.dist-info/RECORD
