Metadata-Version: 2.1
Name: torch-eunn
Version: 0.2.1
Summary: An Efficient Unitary Neural Network implementation for PyTorch
Home-page: https://github.com/flaport/torch_eunn
Author: Floris Laporte
Author-email: floris.laporte@gmail.com
License: UNKNOWN
Platform: UNKNOWN
Classifier: Programming Language :: Python :: 3
Classifier: License :: OSI Approved :: MIT License
Classifier: Operating System :: OS Independent
